{"events":[],"timeStampStates":[{"now":1,"entityStates":[{"name":"predAgent","position":{"x":850,"y":450},"rotation":270,"scale":{"x":1,"y":1},"currentMotiv":null},{"name":"preyAgent","position":{"x":350,"y":450},"rotation":270,"scale":{"x":1,"y":1},"currentMotiv":null}]},{"now":34.333299999999994,"entityStates":[{"name":"predAgent","position":{"x":850,"y":450},"rotation":270,"scale":{"x":1,"y":1},"currentMotiv":null},{"name":"preyAgent","position":{"x":350,"y":450},"rotation":270,"scale":{"x":1,"y":1},"currentMotiv":null}]},{"now":67.6668,"entityStates":[{"name":"predAgent","position":{"x":850,"y":450},"rotation":270,"scale":{"x":1,"y":1},"currentMotiv":null},{"name":"preyAgent","position":{"x":350,"y":450},"rotation":270,"scale":{"x":1,"y":1},"currentMotiv":null}]},{"now":101.00009999999999,"entityStates":[{"name":"predAgent","position":{"x":850,"y":450},"rotation":270,"scale":{"x":1,"y":1},"currentMotiv":null},{"name":"preyAgent","position":{"x":350,"y":450},"rotation":270,"scale":{"x":1,"y":1},"currentMotiv":null}]},{"now":134.33339999999998,"entityStates":[{"name":"predAgent","position":{"x":850,"y":450},"rotation":270,"scale":{"x":1,"y":1},"currentMotiv":null},{"name":"preyAgent","position":{"x":350,"y":450},"rotation":270,"scale":{"x":1,"y":1},"currentMotiv":null}]},{"now":167.6669,"entityStates":[{"name":"predAgent","position":{"x":850,"y":450},"rotation":270,"scale":{"x":1,"y":1},"currentMotiv":null},{"name":"preyAgent","position":{"x":350,"y":450},"rotation":270,"scale":{"x":1,"y":1},"currentMotiv":null}]},{"now":201.00019999999998,"entityStates":[{"name":"predAgent","position":{"x":850,"y":450},"rotation":270,"scale":{"x":1,"y":1},"currentMotiv":null},{"name":"preyAgent","position":{"x":350,"y":450},"rotation":270,"scale":{"x":1,"y":1},"currentMotiv":null}]},{"now":234.3335,"entityStates":[{"name":"predAgent","position":{"x":850,"y":450},"rotation":270,"scale":{"x":1,"y":1},"currentMotiv":null},{"name":"preyAgent","position":{"x":350,"y":450},"rotation":270,"scale":{"x":1,"y":1},"currentMotiv":null}]},{"now":267.667,"entityStates":[{"name":"predAgent","position":{"x":850,"y":450},"rotation":270,"scale":{"x":1,"y":1},"currentMotiv":null},{"name":"preyAgent","position":{"x":350,"y":450},"rotation":270,"scale":{"x":1,"y":1},"currentMotiv":null}]},{"now":301.0003,"entityStates":[{"name":"predAgent","position":{"x":850,"y":450},"rotation":270,"scale":{"x":1,"y":1},"currentMotiv":null},{"name":"preyAgent","position":{"x":350,"y":450},"rotation":270,"scale":{"x":1,"y":1},"currentMotiv":null}]},{"now":334.3336,"entityStates":[{"name":"predAgent","position":{"x":850,"y":450},"rotation":270,"scale":{"x":1,"y":1},"currentMotiv":null},{"name":"preyAgent","position":{"x":350,"y":450},"rotation":270,"scale":{"x":1,"y":1},"currentMotiv":null}]},{"now":367.6671,"entityStates":[{"name":"predAgent","position":{"x":850,"y":450},"rotation":270,"scale":{"x":1,"y":1},"currentMotiv":null},{"name":"preyAgent","position":{"x":350,"y":450},"rotation":270,"scale":{"x":1,"y":1},"currentMotiv":null}]},{"now":401.00039999999996,"entityStates":[{"name":"predAgent","position":{"x":850,"y":450},"rotation":270,"scale":{"x":1,"y":1},"currentMotiv":null},{"name":"preyAgent","position":{"x":350,"y":450},"rotation":270,"scale":{"x":1,"y":1},"currentMotiv":null}]},{"now":434.33369999999996,"entityStates":[{"name":"predAgent","position":{"x":850,"y":450},"rotation":270,"scale":{"x":1,"y":1},"currentMotiv":null},{"name":"preyAgent","position":{"x":350,"y":450},"rotation":270,"scale":{"x":1,"y":1},"currentMotiv":null}]},{"now":467.6672,"entityStates":[{"name":"predAgent","position":{"x":850,"y":450},"rotation":270,"scale":{"x":1,"y":1},"currentMotiv":null},{"name":"preyAgent","position":{"x":350,"y":450},"rotation":270,"scale":{"x":1,"y":1},"currentMotiv":null}]},{"now":501.0005,"entityStates":[{"name":"predAgent","position":{"x":850,"y":450},"rotation":270,"scale":{"x":1,"y":1},"currentMotiv":null},{"name":"preyAgent","position":{"x":350,"y":450},"rotation":270,"scale":{"x":1,"y":1},"currentMotiv":null}]},{"now":534.3338,"entityStates":[{"name":"predAgent","position":{"x":850,"y":450},"rotation":270,"scale":{"x":1,"y":1},"currentMotiv":null},{"name":"preyAgent","position":{"x":350,"y":450},"rotation":270,"scale":{"x":1,"y":1},"currentMotiv":null}]},{"now":567.6673,"entityStates":[{"name":"predAgent","position":{"x":850,"y":450},"rotation":270,"scale":{"x":1,"y":1},"currentMotiv":null},{"name":"preyAgent","position":{"x":350,"y":450},"rotation":270,"scale":{"x":1,"y":1},"currentMotiv":null}]},{"now":601.0006,"entityStates":[{"name":"predAgent","position":{"x":850,"y":450},"rotation":270,"scale":{"x":1,"y":1},"currentMotiv":null},{"name":"preyAgent","position":{"x":350,"y":450},"rotation":270,"scale":{"x":1,"y":1},"currentMotiv":null}]},{"now":634.3339,"entityStates":[{"name":"predAgent","position":{"x":850,"y":450},"rotation":270,"scale":{"x":1,"y":1},"currentMotiv":null},{"name":"preyAgent","position":{"x":350,"y":450},"rotation":270,"scale":{"x":1,"y":1},"currentMotiv":null}]},{"now":667.6674,"entityStates":[{"name":"predAgent","position":{"x":850,"y":450},"rotation":270,"scale":{"x":1,"y":1},"currentMotiv":null},{"name":"preyAgent","position":{"x":350,"y":450},"rotation":270,"scale":{"x":1,"y":1},"currentMotiv":null}]},{"now":701.0007,"entityStates":[{"name":"predAgent","position":{"x":850,"y":450},"rotation":270,"scale":{"x":1,"y":1},"currentMotiv":null},{"name":"preyAgent","position":{"x":350,"y":450},"rotation":270,"scale":{"x":1,"y":1},"currentMotiv":null}]},{"now":734.3340000000001,"entityStates":[{"name":"predAgent","position":{"x":850,"y":450},"rotation":270,"scale":{"x":1,"y":1},"currentMotiv":null},{"name":"preyAgent","position":{"x":350,"y":450},"rotation":270,"scale":{"x":1,"y":1},"currentMotiv":null}]},{"now":767.6674999999999,"entityStates":[{"name":"predAgent","position":{"x":850,"y":450},"rotation":270,"scale":{"x":1,"y":1},"currentMotiv":null},{"name":"preyAgent","position":{"x":350,"y":450},"rotation":270,"scale":{"x":1,"y":1},"currentMotiv":null}]},{"now":801.0007999999999,"entityStates":[{"name":"predAgent","position":{"x":850,"y":450},"rotation":270,"scale":{"x":1,"y":1},"currentMotiv":null},{"name":"preyAgent","position":{"x":350,"y":450},"rotation":270,"scale":{"x":1,"y":1},"currentMotiv":null}]},{"now":834.3340999999999,"entityStates":[{"name":"predAgent","position":{"x":850,"y":450},"rotation":270,"scale":{"x":1,"y":1},"currentMotiv":null},{"name":"preyAgent","position":{"x":350,"y":450},"rotation":270,"scale":{"x":1,"y":1},"currentMotiv":null}]},{"now":867.6676,"entityStates":[{"name":"predAgent","position":{"x":850,"y":450},"rotation":270,"scale":{"x":1,"y":1},"currentMotiv":null},{"name":"preyAgent","position":{"x":350,"y":450},"rotation":270,"scale":{"x":1,"y":1},"currentMotiv":null}]},{"now":901.0009,"entityStates":[{"name":"predAgent","position":{"x":850,"y":450},"rotation":270,"scale":{"x":1,"y":1},"currentMotiv":null},{"name":"preyAgent","position":{"x":350,"y":450},"rotation":270,"scale":{"x":1,"y":1},"currentMotiv":null}]},{"now":934.3342,"entityStates":[{"name":"predAgent","position":{"x":850,"y":450},"rotation":270,"scale":{"x":1,"y":1},"currentMotiv":null},{"name":"preyAgent","position":{"x":350,"y":450},"rotation":270,"scale":{"x":1,"y":1},"currentMotiv":null}]},{"now":967.6677,"entityStates":[{"name":"predAgent","position":{"x":850,"y":450},"rotation":270,"scale":{"x":1,"y":1},"currentMotiv":null},{"name":"preyAgent","position":{"x":350,"y":450},"rotation":270,"scale":{"x":1,"y":1},"currentMotiv":null}]},{"now":1001.001,"entityStates":[{"name":"predAgent","position":{"x":850,"y":450},"rotation":270,"scale":{"x":1,"y":1},"currentMotiv":null},{"name":"preyAgent","position":{"x":350,"y":450},"rotation":270,"scale":{"x":1,"y":1},"currentMotiv":null}]},{"now":1034.3343,"entityStates":[{"name":"predAgent","position":{"x":850.19578928833,"y":448.5128327079393},"rotation":270,"scale":{"x":1,"y":1},"currentMotiv":"wander_predAgent"},{"name":"preyAgent","position":{"x":349.71841796292756,"y":448.22216098692877},"rotation":270,"scale":{"x":1,"y":1},"currentMotiv":"wander_preyAgent"}]},{"now":1067.6678,"entityStates":[{"name":"predAgent","position":{"x":851.0783772337729,"y":446.12046117472545},"rotation":270,"scale":{"x":1,"y":1},"currentMotiv":"wander_predAgent"},{"name":"preyAgent","position":{"x":348.5655298019089,"y":445.3877180102805},"rotation":270,"scale":{"x":1,"y":1},"currentMotiv":"wander_preyAgent"}]},{"now":1101.0011,"entityStates":[{"name":"predAgent","position":{"x":853.0401457684883,"y":443.4859792809156},"rotation":270,"scale":{"x":1,"y":1},"currentMotiv":"wander_predAgent"},{"name":"preyAgent","position":{"x":346.61112456316806,"y":441.9644497634709},"rotation":270,"scale":{"x":1,"y":1},"currentMotiv":"wander_preyAgent"}]},{"now":1134.3344,"entityStates":[{"name":"predAgent","position":{"x":856.1770055496728,"y":441.3434902819563},"rotation":270,"scale":{"x":1,"y":1},"currentMotiv":"wander_predAgent"},{"name":"preyAgent","position":{"x":344.0522621471979,"y":438.1909323650122},"rotation":270,"scale":{"x":1,"y":1},"currentMotiv":"wander_preyAgent"}]},{"now":1167.6679000000001,"entityStates":[{"name":"predAgent","position":{"x":864.5830863601086,"y":441.0233160242327},"rotation":270,"scale":{"x":1,"y":1},"currentMotiv":"wander_predAgent"},{"name":"preyAgent","position":{"x":337.723341313769,"y":430.08597052890565},"rotation":270,"scale":{"x":1,"y":1},"currentMotiv":"wander_preyAgent"}]},{"now":1201.0012000000002,"entityStates":[{"name":"predAgent","position":{"x":868.4965555629597,"y":443.4174379686114},"rotation":270,"scale":{"x":1,"y":1},"currentMotiv":"wander_predAgent"},{"name":"preyAgent","position":{"x":334.1403427415386,"y":425.90606703450527},"rotation":270,"scale":{"x":1,"y":1},"currentMotiv":"wander_preyAgent"}]},{"now":1234.3345,"entityStates":[{"name":"predAgent","position":{"x":871.6447529607709,"y":446.9225384757136},"rotation":270,"scale":{"x":1,"y":1},"currentMotiv":"wander_predAgent"},{"name":"preyAgent","position":{"x":330.4102438573595,"y":421.65751038403613},"rotation":270,"scale":{"x":1,"y":1},"currentMotiv":"wander_preyAgent"}]},{"now":1267.6680000000001,"entityStates":[{"name":"predAgent","position":{"x":874.2228749980957,"y":450.96841905884753},"rotation":270,"scale":{"x":1,"y":1},"currentMotiv":"wander_predAgent"},{"name":"preyAgent","position":{"x":326.61544893313055,"y":417.3280093568736},"rotation":270,"scale":{"x":1,"y":1},"currentMotiv":"wander_preyAgent"}]},{"now":1301.0013000000001,"entityStates":[{"name":"predAgent","position":{"x":876.4246879392645,"y":455.2990497427309},"rotation":270,"scale":{"x":1,"y":1},"currentMotiv":"wander_predAgent"},{"name":"preyAgent","position":{"x":322.7835788888568,"y":412.9341919945738},"rotation":270,"scale":{"x":1,"y":1},"currentMotiv":"wander_preyAgent"}]},{"now":1334.3346000000001,"entityStates":[{"name":"predAgent","position":{"x":878.3654064399807,"y":459.79901773856875},"rotation":270,"scale":{"x":1,"y":1},"currentMotiv":"wander_predAgent"},{"name":"preyAgent","position":{"x":318.92369438212603,"y":408.4971412980645},"rotation":270,"scale":{"x":1,"y":1},"currentMotiv":"wander_preyAgent"}]},{"now":1367.6680999999999,"entityStates":[{"name":"predAgent","position":{"x":880.105718139304,"y":464.41168155411276},"rotation":270,"scale":{"x":1,"y":1},"currentMotiv":"wander_predAgent"},{"name":"preyAgent","position":{"x":315.0421233433145,"y":404.0316388903627},"rotation":270,"scale":{"x":1,"y":1},"currentMotiv":"wander_preyAgent"}]},{"now":1401.0013999999999,"entityStates":[{"name":"predAgent","position":{"x":881.7209227262808,"y":469.0918324342078},"rotation":270,"scale":{"x":1,"y":1},"currentMotiv":"wander_predAgent"},{"name":"preyAgent","position":{"x":311.1483892562139,"y":399.5436045439913},"rotation":270,"scale":{"x":1,"y":1},"currentMotiv":"wander_preyAgent"}]},{"now":1434.3346999999999,"entityStates":[{"name":"predAgent","position":{"x":883.2653985702319,"y":473.8112520490106},"rotation":270,"scale":{"x":1,"y":1},"currentMotiv":"wander_predAgent"},{"name":"preyAgent","position":{"x":307.25539849717177,"y":395.03183315806433},"rotation":270,"scale":{"x":1,"y":1},"currentMotiv":"wander_preyAgent"}]},{"now":1467.6682,"entityStates":[{"name":"predAgent","position":{"x":886.3547778838831,"y":483.2781188035858},"rotation":270,"scale":{"x":1,"y":1},"currentMotiv":"wander_predAgent"},{"name":"preyAgent","position":{"x":299.5374039617379,"y":385.90770570363355},"rotation":270,"scale":{"x":1,"y":1},"currentMotiv":"wander_preyAgent"}]},{"now":1501.0015,"entityStates":[{"name":"predAgent","position":{"x":887.9816730386137,"y":487.99266440448037},"rotation":270,"scale":{"x":1,"y":1},"currentMotiv":"wander_predAgent"},{"name":"preyAgent","position":{"x":295.76052348533983,"y":381.26454215759975},"rotation":270,"scale":{"x":1,"y":1},"currentMotiv":"wander_preyAgent"}]},{"now":1534.3348,"entityStates":[{"name":"predAgent","position":{"x":889.6683979187137,"y":492.6900290514943},"rotation":270,"scale":{"x":1,"y":1},"currentMotiv":"wander_predAgent"},{"name":"preyAgent","position":{"x":292.03534844017673,"y":376.57426502089953},"rotation":270,"scale":{"x":1,"y":1},"currentMotiv":"wander_preyAgent"}]},{"now":1567.6683,"entityStates":[{"name":"predAgent","position":{"x":891.4365548609507,"y":497.35966619662446},"rotation":270,"scale":{"x":1,"y":1},"currentMotiv":"wander_predAgent"},{"name":"preyAgent","position":{"x":288.3882228578682,"y":371.8199380160344},"rotation":270,"scale":{"x":1,"y":1},"currentMotiv":"wander_preyAgent"}]},{"now":1601.0016,"entityStates":[{"name":"predAgent","position":{"x":893.2401885875685,"y":502.0178586024682},"rotation":270,"scale":{"x":1,"y":1},"currentMotiv":"wander_predAgent"},{"name":"preyAgent","position":{"x":284.8163836988825,"y":367.0061274909696},"rotation":270,"scale":{"x":1,"y":1},"currentMotiv":"wander_preyAgent"}]},{"now":1634.3349,"entityStates":[{"name":"predAgent","position":{"x":895.1111978800216,"y":506.65036251888813},"rotation":270,"scale":{"x":1,"y":1},"currentMotiv":"wander_predAgent"},{"name":"preyAgent","position":{"x":281.3118043370118,"y":362.14116440990364},"rotation":270,"scale":{"x":1,"y":1},"currentMotiv":"wander_preyAgent"}]},{"now":1667.6684,"entityStates":[{"name":"predAgent","position":{"x":897.0523095500024,"y":511.2549591826462},"rotation":270,"scale":{"x":1,"y":1},"currentMotiv":"wander_predAgent"},{"name":"preyAgent","position":{"x":277.84694400254824,"y":357.24630010564454},"rotation":270,"scale":{"x":1,"y":1},"currentMotiv":"wander_preyAgent"}]},{"now":1701.0017,"entityStates":[{"name":"predAgent","position":{"x":899.0337127007654,"y":515.8433346584904},"rotation":270,"scale":{"x":1,"y":1},"currentMotiv":"wander_predAgent"},{"name":"preyAgent","position":{"x":274.43660709677556,"y":352.31253991844085},"rotation":270,"scale":{"x":1,"y":1},"currentMotiv":"wander_preyAgent"}]},{"now":1734.335,"entityStates":[{"name":"predAgent","position":{"x":901.0547471673303,"y":520.4150063185982},"rotation":270,"scale":{"x":1,"y":1},"currentMotiv":"wander_predAgent"},{"name":"preyAgent","position":{"x":271.0688924353324,"y":347.3487862241656},"rotation":270,"scale":{"x":1,"y":1},"currentMotiv":"wander_preyAgent"}]},{"now":1767.6685,"entityStates":[{"name":"predAgent","position":{"x":905.3175900460091,"y":529.4568048189008},"rotation":270,"scale":{"x":1,"y":1},"currentMotiv":"wander_predAgent"},{"name":"preyAgent","position":{"x":264.5327041145881,"y":337.28883390435084},"rotation":270,"scale":{"x":1,"y":1},"currentMotiv":"wander_preyAgent"}]},{"now":1801.0018,"entityStates":[{"name":"predAgent","position":{"x":907.557044578167,"y":533.9258771038113},"rotation":270,"scale":{"x":1,"y":1},"currentMotiv":"wander_predAgent"},{"name":"preyAgent","position":{"x":261.32937258619165,"y":332.2166113779054},"rotation":270,"scale":{"x":1,"y":1},"currentMotiv":"wander_preyAgent"}]},{"now":1834.3351,"entityStates":[{"name":"predAgent","position":{"x":909.8719053632547,"y":538.3563494281269},"rotation":270,"scale":{"x":1,"y":1},"currentMotiv":"wander_predAgent"},{"name":"preyAgent","position":{"x":258.16223861004136,"y":327.1214705376356},"rotation":270,"scale":{"x":1,"y":1},"currentMotiv":"wander_preyAgent"}]},{"now":1867.6686,"entityStates":[{"name":"predAgent","position":{"x":912.2236046473532,"y":542.7677755621512},"rotation":270,"scale":{"x":1,"y":1},"currentMotiv":"wander_predAgent"},{"name":"preyAgent","position":{"x":255.05842321343783,"y":321.9877647882579},"rotation":270,"scale":{"x":1,"y":1},"currentMotiv":"wander_preyAgent"}]},{"now":1901.0019,"entityStates":[{"name":"predAgent","position":{"x":914.5964324318645,"y":547.1681738073522},"rotation":270,"scale":{"x":1,"y":1},"currentMotiv":"wander_predAgent"},{"name":"preyAgent","position":{"x":252.0238349400174,"y":316.81278775500124},"rotation":270,"scale":{"x":1,"y":1},"currentMotiv":"wander_preyAgent"}]},{"now":1934.3352,"entityStates":[{"name":"predAgent","position":{"x":916.968976809406,"y":551.5688808799899},"rotation":270,"scale":{"x":1,"y":1},"currentMotiv":"wander_predAgent"},{"name":"preyAgent","position":{"x":249.01681430519363,"y":311.62148621331636},"rotation":270,"scale":{"x":1,"y":1},"currentMotiv":"wander_preyAgent"}]},{"now":1967.6687,"entityStates":[{"name":"predAgent","position":{"x":919.3224121549009,"y":555.9798837575643},"rotation":270,"scale":{"x":1,"y":1},"currentMotiv":"wander_predAgent"},{"name":"preyAgent","position":{"x":246.01400776309407,"y":306.4275523868344},"rotation":270,"scale":{"x":1,"y":1},"currentMotiv":"wander_preyAgent"}]},{"now":2001.0020000000002,"entityStates":[{"name":"predAgent","position":{"x":921.6795336031522,"y":560.3889929520708},"rotation":270,"scale":{"x":1,"y":1},"currentMotiv":"wander_predAgent"},{"name":"preyAgent","position":{"x":242.9967796130161,"y":301.24188619258297},"rotation":270,"scale":{"x":1,"y":1},"currentMotiv":"wander_preyAgent"}]},{"now":2034.3353,"entityStates":[{"name":"predAgent","position":{"x":924.04111827228,"y":564.7958387031982},"rotation":270,"scale":{"x":1,"y":1},"currentMotiv":"wander_predAgent"},{"name":"preyAgent","position":{"x":239.95016440121833,"y":296.0734045110988},"rotation":270,"scale":{"x":1,"y":1},"currentMotiv":"wander_preyAgent"}]},{"now":2067.6688,"entityStates":[{"name":"predAgent","position":{"x":928.6068764740432,"y":573.6902932167701},"rotation":270,"scale":{"x":1,"y":1},"currentMotiv":"wander_predAgent"},{"name":"preyAgent","position":{"x":233.77964371025658,"y":285.7823713643669},"rotation":270,"scale":{"x":1,"y":1},"currentMotiv":"wander_preyAgent"}]},{"now":2101.0021,"entityStates":[{"name":"predAgent","position":{"x":930.7957025609069,"y":578.1848142677163},"rotation":270,"scale":{"x":1,"y":1},"currentMotiv":"wander_predAgent"},{"name":"preyAgent","position":{"x":230.69575172272621,"y":280.63589889886947},"rotation":270,"scale":{"x":1,"y":1},"currentMotiv":"wander_preyAgent"}]},{"now":2134.3354,"entityStates":[{"name":"predAgent","position":{"x":932.8821284952797,"y":582.7267819095107},"rotation":270,"scale":{"x":1,"y":1},"currentMotiv":"wander_predAgent"},{"name":"preyAgent","position":{"x":227.60850642565782,"y":275.4913426900862},"rotation":270,"scale":{"x":1,"y":1},"currentMotiv":"wander_preyAgent"}]},{"now":2167.6688999999997,"entityStates":[{"name":"predAgent","position":{"x":934.8458718628949,"y":587.322623401102},"rotation":270,"scale":{"x":1,"y":1},"currentMotiv":"wander_predAgent"},{"name":"preyAgent","position":{"x":224.52108838617445,"y":270.34681948702604},"rotation":270,"scale":{"x":1,"y":1},"currentMotiv":"wander_preyAgent"}]},{"now":2201.0022,"entityStates":[{"name":"predAgent","position":{"x":936.7042408648454,"y":591.9625097897098},"rotation":270,"scale":{"x":1,"y":1},"currentMotiv":"wander_predAgent"},{"name":"preyAgent","position":{"x":221.41211130851275,"y":265.2153828565364},"rotation":270,"scale":{"x":1,"y":1},"currentMotiv":"wander_preyAgent"}]},{"now":2234.3354999999997,"entityStates":[{"name":"predAgent","position":{"x":938.4398822084072,"y":596.6493197884872},"rotation":270,"scale":{"x":1,"y":1},"currentMotiv":"wander_predAgent"},{"name":"preyAgent","position":{"x":218.2933853917477,"y":260.08979183976624},"rotation":270,"scale":{"x":1,"y":1},"currentMotiv":"wander_preyAgent"}]},{"now":2267.6690000000003,"entityStates":[{"name":"predAgent","position":{"x":940.0272302811817,"y":601.3876469213338},"rotation":270,"scale":{"x":1,"y":1},"currentMotiv":"wander_predAgent"},{"name":"preyAgent","position":{"x":215.14929153105834,"y":254.97978276738863},"rotation":270,"scale":{"x":1,"y":1},"currentMotiv":"wander_preyAgent"}]},{"now":2301.0023,"entityStates":[{"name":"predAgent","position":{"x":941.4913760151993,"y":606.1660856246519},"rotation":270,"scale":{"x":1,"y":1},"currentMotiv":"wander_predAgent"},{"name":"preyAgent","position":{"x":211.99393199798726,"y":249.87665422146938},"rotation":270,"scale":{"x":1,"y":1},"currentMotiv":"wander_preyAgent"}]},{"now":2334.3356000000003,"entityStates":[{"name":"predAgent","position":{"x":942.8364412109582,"y":610.9796119550035},"rotation":270,"scale":{"x":1,"y":1},"currentMotiv":"wander_predAgent"},{"name":"preyAgent","position":{"x":208.8226709729566,"y":244.78336505047028},"rotation":270,"scale":{"x":1,"y":1},"currentMotiv":"wander_preyAgent"}]},{"now":2367.6691,"entityStates":[{"name":"predAgent","position":{"x":945.3334833292591,"y":620.6601578922775},"rotation":270,"scale":{"x":1,"y":1},"currentMotiv":"wander_predAgent"},{"name":"preyAgent","position":{"x":202.5014479843876,"y":234.5835958942651},"rotation":270,"scale":{"x":1,"y":1},"currentMotiv":"wander_preyAgent"}]},{"now":2401.0024,"entityStates":[{"name":"predAgent","position":{"x":946.5569413201929,"y":625.5072560697953},"rotation":270,"scale":{"x":1,"y":1},"currentMotiv":"wander_predAgent"},{"name":"preyAgent","position":{"x":199.34765677638705,"y":229.47941951783096},"rotation":270,"scale":{"x":1,"y":1},"currentMotiv":"wander_preyAgent"}]},{"now":2434.3357,"entityStates":[{"name":"predAgent","position":{"x":947.7867930506292,"y":630.3529946604641},"rotation":270,"scale":{"x":1,"y":1},"currentMotiv":"wander_predAgent"},{"name":"preyAgent","position":{"x":196.21517192555027,"y":224.3622165338129},"rotation":270,"scale":{"x":1,"y":1},"currentMotiv":"wander_preyAgent"}]},{"now":2467.6692,"entityStates":[{"name":"predAgent","position":{"x":949.0663589508623,"y":635.1855173087454},"rotation":270,"scale":{"x":1,"y":1},"currentMotiv":"wander_predAgent"},{"name":"preyAgent","position":{"x":193.09048497283328,"y":219.24020372421472},"rotation":270,"scale":{"x":1,"y":1},"currentMotiv":"wander_preyAgent"}]},{"now":2501.0024999999996,"entityStates":[{"name":"predAgent","position":{"x":950.3670455665409,"y":640.0126722982244},"rotation":270,"scale":{"x":1,"y":1},"currentMotiv":"wander_predAgent"},{"name":"preyAgent","position":{"x":189.95686161420366,"y":214.12367037234307},"rotation":270,"scale":{"x":1,"y":1},"currentMotiv":"wander_preyAgent"}]},{"now":2534.3358,"entityStates":[{"name":"predAgent","position":{"x":951.6519630278722,"y":644.8440598793376},"rotation":270,"scale":{"x":1,"y":1},"currentMotiv":"wander_predAgent"},{"name":"preyAgent","position":{"x":186.83104183459153,"y":209.0023740927357},"rotation":270,"scale":{"x":1,"y":1},"currentMotiv":"wander_preyAgent"}]},{"now":2567.6693,"entityStates":[{"name":"predAgent","position":{"x":952.9575418233713,"y":649.6698879207491},"rotation":270,"scale":{"x":1,"y":1},"currentMotiv":"wander_predAgent"},{"name":"preyAgent","position":{"x":183.7413105158122,"y":203.85946901671943},"rotation":270,"scale":{"x":1,"y":1},"currentMotiv":"wander_preyAgent"}]},{"now":2601.0026000000003,"entityStates":[{"name":"predAgent","position":{"x":954.3286779391004,"y":654.4770035097378},"rotation":270,"scale":{"x":1,"y":1},"currentMotiv":"wander_predAgent"},{"name":"preyAgent","position":{"x":180.69228917055912,"y":198.69231188809587},"rotation":270,"scale":{"x":1,"y":1},"currentMotiv":"wander_preyAgent"}]},{"now":2634.3359,"entityStates":[{"name":"predAgent","position":{"x":955.720041930131,"y":659.2785742779156},"rotation":270,"scale":{"x":1,"y":1},"currentMotiv":"wander_predAgent"},{"name":"preyAgent","position":{"x":177.7057520278232,"y":193.48908570974478},"rotation":270,"scale":{"x":1,"y":1},"currentMotiv":"wander_preyAgent"}]},{"now":2667.6693999999998,"entityStates":[{"name":"predAgent","position":{"x":958.3469394608137,"y":668.9236957746956},"rotation":270,"scale":{"x":1,"y":1},"currentMotiv":"wander_predAgent"},{"name":"preyAgent","position":{"x":171.84253640059313,"y":183.01988199226588},"rotation":270,"scale":{"x":1,"y":1},"currentMotiv":"wander_preyAgent"}]},{"now":2701.0027,"entityStates":[{"name":"predAgent","position":{"x":959.5367660412204,"y":673.7784886793876},"rotation":270,"scale":{"x":1,"y":1},"currentMotiv":"wander_predAgent"},{"name":"preyAgent","position":{"x":168.9850406236133,"y":177.74468058832306},"rotation":270,"scale":{"x":1,"y":1},"currentMotiv":"wander_preyAgent"}]},{"now":2734.336,"entityStates":[{"name":"predAgent","position":{"x":960.7225778618665,"y":678.6342868243721},"rotation":270,"scale":{"x":1,"y":1},"currentMotiv":"wander_predAgent"},{"name":"preyAgent","position":{"x":166.17272930054867,"y":172.44508351510945},"rotation":270,"scale":{"x":1,"y":1},"currentMotiv":"wander_preyAgent"}]},{"now":2767.6695,"entityStates":[{"name":"predAgent","position":{"x":961.9712534034121,"y":683.4737196772594},"rotation":270,"scale":{"x":1,"y":1},"currentMotiv":"wander_predAgent"},{"name":"preyAgent","position":{"x":163.38408256787451,"y":167.13285321058208},"rotation":270,"scale":{"x":1,"y":1},"currentMotiv":"wander_preyAgent"}]},{"now":2801.0028,"entityStates":[{"name":"predAgent","position":{"x":963.3024186723017,"y":688.291261732974},"rotation":270,"scale":{"x":1,"y":1},"currentMotiv":"wander_predAgent"},{"name":"preyAgent","position":{"x":160.6302461681408,"y":161.80250346058315},"rotation":270,"scale":{"x":1,"y":1},"currentMotiv":"wander_preyAgent"}]},{"now":2834.3361,"entityStates":[{"name":"predAgent","position":{"x":964.7229425847598,"y":693.0834149952569},"rotation":270,"scale":{"x":1,"y":1},"currentMotiv":"wander_predAgent"},{"name":"preyAgent","position":{"x":157.90852500537974,"y":156.45561172580267},"rotation":270,"scale":{"x":1,"y":1},"currentMotiv":"wander_preyAgent"}]},{"now":2867.6696,"entityStates":[{"name":"predAgent","position":{"x":966.1832124084561,"y":697.8641037501964},"rotation":270,"scale":{"x":1,"y":1},"currentMotiv":"wander_predAgent"},{"name":"preyAgent","position":{"x":155.20176121609063,"y":151.10105394572574},"rotation":270,"scale":{"x":1,"y":1},"currentMotiv":"wander_preyAgent"}]},{"now":2901.0029,"entityStates":[{"name":"predAgent","position":{"x":967.694157094328,"y":702.6292305997272},"rotation":270,"scale":{"x":1,"y":1},"currentMotiv":"wander_predAgent"},{"name":"preyAgent","position":{"x":152.46910534325573,"y":145.75992523552492},"rotation":270,"scale":{"x":1,"y":1},"currentMotiv":"wander_preyAgent"}]},{"now":2934.3362,"entityStates":[{"name":"predAgent","position":{"x":969.2820276396201,"y":707.3690452342873},"rotation":270,"scale":{"x":1,"y":1},"currentMotiv":"wander_predAgent"},{"name":"preyAgent","position":{"x":149.68698550820685,"y":140.44456205288807},"rotation":270,"scale":{"x":1,"y":1},"currentMotiv":"wander_preyAgent"}]},{"now":2967.6697,"entityStates":[{"name":"predAgent","position":{"x":972.7107395344435,"y":716.759235148075},"rotation":270,"scale":{"x":1,"y":1},"currentMotiv":"wander_predAgent"},{"name":"preyAgent","position":{"x":143.98624561311863,"y":129.88633914492146},"rotation":270,"scale":{"x":1,"y":1},"currentMotiv":"wander_preyAgent"}]},{"now":3001.0029999999997,"entityStates":[{"name":"predAgent","position":{"x":974.5904225285358,"y":721.3904643319411},"rotation":270,"scale":{"x":1,"y":1},"currentMotiv":"wander_predAgent"},{"name":"preyAgent","position":{"x":141.053847980862,"y":124.65229036565391},"rotation":270,"scale":{"x":1,"y":1},"currentMotiv":"wander_preyAgent"}]},{"now":3034.3363,"entityStates":[{"name":"predAgent","position":{"x":976.5708943353442,"y":725.9797823658035},"rotation":270,"scale":{"x":1,"y":1},"currentMotiv":"wander_predAgent"},{"name":"preyAgent","position":{"x":138.04874290495508,"y":119.45992557476825},"rotation":270,"scale":{"x":1,"y":1},"currentMotiv":"wander_preyAgent"}]},{"now":3067.6698,"entityStates":[{"name":"predAgent","position":{"x":978.5858247410298,"y":730.5544055329844},"rotation":270,"scale":{"x":1,"y":1},"currentMotiv":"wander_predAgent"},{"name":"preyAgent","position":{"x":134.9792906033324,"y":114.30521274055272},"rotation":270,"scale":{"x":1,"y":1},"currentMotiv":"wander_preyAgent"}]},{"now":3101.0031,"entityStates":[{"name":"predAgent","position":{"x":980.6143765335305,"y":735.1234129183622},"rotation":270,"scale":{"x":1,"y":1},"currentMotiv":"wander_predAgent"},{"name":"preyAgent","position":{"x":131.86172043641633,"y":109.17926979505651},"rotation":270,"scale":{"x":1,"y":1},"currentMotiv":"wander_preyAgent"}]},{"now":3134.3364,"entityStates":[{"name":"predAgent","position":{"x":982.6737219302918,"y":739.6787740361774},"rotation":270,"scale":{"x":1,"y":1},"currentMotiv":"wander_predAgent"},{"name":"preyAgent","position":{"x":128.70870206131136,"y":104.07490778371226},"rotation":270,"scale":{"x":1,"y":1},"currentMotiv":"wander_preyAgent"}]},{"now":3167.6699,"entityStates":[{"name":"predAgent","position":{"x":984.7617066023971,"y":744.2213057433311},"rotation":270,"scale":{"x":1,"y":1},"currentMotiv":"wander_predAgent"},{"name":"preyAgent","position":{"x":125.51459140842908,"y":98.99616305343692},"rotation":270,"scale":{"x":1,"y":1},"currentMotiv":"wander_preyAgent"}]},{"now":3201.0032,"entityStates":[{"name":"predAgent","position":{"x":986.8518908433741,"y":748.7629483258323},"rotation":270,"scale":{"x":1,"y":1},"currentMotiv":"wander_predAgent"},{"name":"preyAgent","position":{"x":122.30865025162412,"y":93.9248095997957},"rotation":270,"scale":{"x":1,"y":1},"currentMotiv":"wander_preyAgent"}]},{"now":3234.3365,"entityStates":[{"name":"predAgent","position":{"x":988.9045824133893,"y":753.3213690157135},"rotation":270,"scale":{"x":1,"y":1},"currentMotiv":"wander_predAgent"},{"name":"preyAgent","position":{"x":119.08307771955864,"y":88.86587013619138},"rotation":270,"scale":{"x":1,"y":1},"currentMotiv":"wander_preyAgent"}]},{"now":3267.67,"entityStates":[{"name":"predAgent","position":{"x":992.9628616300529,"y":762.4594865953455},"rotation":270,"scale":{"x":1,"y":1},"currentMotiv":"wander_predAgent"},{"name":"preyAgent","position":{"x":112.47779004479172,"y":78.84909984555577},"rotation":270,"scale":{"x":1,"y":1},"currentMotiv":"wander_preyAgent"}]},{"now":3301.0033000000003,"entityStates":[{"name":"predAgent","position":{"x":994.9049388784886,"y":767.065706772289},"rotation":270,"scale":{"x":1,"y":1},"currentMotiv":"wander_predAgent"},{"name":"preyAgent","position":{"x":109.0817879105053,"y":73.90343638682452},"rotation":270,"scale":{"x":1,"y":1},"currentMotiv":"wander_preyAgent"}]},{"now":3334.3366,"entityStates":[{"name":"predAgent","position":{"x":996.8244897829545,"y":771.6816085780828},"rotation":270,"scale":{"x":1,"y":1},"currentMotiv":"wander_predAgent"},{"name":"preyAgent","position":{"x":105.60371317392514,"y":69.01564504964237},"rotation":270,"scale":{"x":1,"y":1},"currentMotiv":"wander_preyAgent"}]},{"now":3367.6701000000003,"entityStates":[{"name":"predAgent","position":{"x":998.7411520730743,"y":776.2989637476674},"rotation":270,"scale":{"x":1,"y":1},"currentMotiv":"wander_predAgent"},{"name":"preyAgent","position":{"x":102.07224595684627,"y":64.16590982706788},"rotation":270,"scale":{"x":1,"y":1},"currentMotiv":"wander_preyAgent"}]},{"now":3401.0034,"entityStates":[{"name":"predAgent","position":{"x":1000.6477226085045,"y":780.9206841828993},"rotation":270,"scale":{"x":1,"y":1},"currentMotiv":"wander_predAgent"},{"name":"preyAgent","position":{"x":98.50380168413116,"y":59.34305284358502},"rotation":270,"scale":{"x":1,"y":1},"currentMotiv":"wander_preyAgent"}]},{"now":3434.3367,"entityStates":[{"name":"predAgent","position":{"x":1002.5848724782508,"y":785.5294402081603},"rotation":270,"scale":{"x":1,"y":1},"currentMotiv":"wander_predAgent"},{"name":"preyAgent","position":{"x":94.92201775373276,"y":54.529927175558505},"rotation":270,"scale":{"x":1,"y":1},"currentMotiv":"wander_preyAgent"}]},{"now":3467.6702,"entityStates":[{"name":"predAgent","position":{"x":1004.5760121691148,"y":790.114985327707},"rotation":270,"scale":{"x":1,"y":1},"currentMotiv":"wander_predAgent"},{"name":"preyAgent","position":{"x":91.29538130182664,"y":49.75086344660687},"rotation":270,"scale":{"x":1,"y":1},"currentMotiv":"wander_preyAgent"}]},{"now":3501.0035,"entityStates":[{"name":"predAgent","position":{"x":1006.6543596103105,"y":794.6610402927342},"rotation":270,"scale":{"x":1,"y":1},"currentMotiv":"wander_predAgent"},{"name":"preyAgent","position":{"x":87.58179346718632,"y":45.040188958155106},"rotation":270,"scale":{"x":1,"y":1},"currentMotiv":"wander_preyAgent"}]},{"now":3534.3368,"entityStates":[{"name":"predAgent","position":{"x":1008.7946915431671,"y":799.178674811344},"rotation":270,"scale":{"x":1,"y":1},"currentMotiv":"wander_predAgent"},{"name":"preyAgent","position":{"x":83.79437192597238,"y":40.388251369983315},"rotation":270,"scale":{"x":1,"y":1},"currentMotiv":"wander_preyAgent"}]},{"now":3567.6703,"entityStates":[{"name":"predAgent","position":{"x":1013.1010954754468,"y":808.2022924087129},"rotation":270,"scale":{"x":1,"y":1},"currentMotiv":"wander_predAgent"},{"name":"preyAgent","position":{"x":76.79425740765548,"y":33.86932190112309},"rotation":270,"scale":{"x":1,"y":1},"currentMotiv":"wander_preyAgent"}]},{"now":3601.0036,"entityStates":[{"name":"predAgent","position":{"x":1015.2673385211867,"y":812.7080629757346},"rotation":270,"scale":{"x":1,"y":1},"currentMotiv":"wander_predAgent"},{"name":"preyAgent","position":{"x":73.01156555280537,"y":33.05271949099342},"rotation":270,"scale":{"x":1,"y":1},"currentMotiv":"wander_preyAgent"}]},{"now":3634.3369000000002,"entityStates":[{"name":"predAgent","position":{"x":1017.4613830642138,"y":817.2004386701944},"rotation":270,"scale":{"x":1,"y":1},"currentMotiv":"wander_predAgent"},{"name":"preyAgent","position":{"x":68.65355381694343,"y":33.81646181357837},"rotation":270,"scale":{"x":1,"y":1},"currentMotiv":"wander_preyAgent"}]},{"now":3667.6704,"entityStates":[{"name":"predAgent","position":{"x":1019.7114214384653,"y":821.6647046066863},"rotation":270,"scale":{"x":1,"y":1},"currentMotiv":"wander_predAgent"},{"name":"preyAgent","position":{"x":64.81822992374595,"y":36.282313481062},"rotation":270,"scale":{"x":1,"y":1},"currentMotiv":"wander_preyAgent"}]},{"now":3701.0036999999998,"entityStates":[{"name":"predAgent","position":{"x":1022.0554486039109,"y":826.0794138864634},"rotation":270,"scale":{"x":1,"y":1},"currentMotiv":"wander_predAgent"},{"name":"preyAgent","position":{"x":61.640406418384934,"y":40.12851612904976},"rotation":270,"scale":{"x":1,"y":1},"currentMotiv":"wander_preyAgent"}]},{"now":3734.337,"entityStates":[{"name":"predAgent","position":{"x":1024.4637311624647,"y":830.4599249588122},"rotation":270,"scale":{"x":1,"y":1},"currentMotiv":"wander_predAgent"},{"name":"preyAgent","position":{"x":59.073257537482974,"y":44.756623380852865},"rotation":270,"scale":{"x":1,"y":1},"currentMotiv":"wander_preyAgent"}]},{"now":3767.6704999999997,"entityStates":[{"name":"predAgent","position":{"x":1026.9161115711402,"y":834.8162794293177},"rotation":270,"scale":{"x":1,"y":1},"currentMotiv":"wander_predAgent"},{"name":"preyAgent","position":{"x":56.99609405478679,"y":49.85387380180282},"rotation":270,"scale":{"x":1,"y":1},"currentMotiv":"wander_preyAgent"}]},{"now":3801.0038,"entityStates":[{"name":"predAgent","position":{"x":1029.416391872309,"y":839.1454374641227},"rotation":270,"scale":{"x":1,"y":1},"currentMotiv":"wander_predAgent"},{"name":"preyAgent","position":{"x":55.272964229866105,"y":55.23762393016373},"rotation":270,"scale":{"x":1,"y":1},"currentMotiv":"wander_preyAgent"}]},{"now":3834.3370999999997,"entityStates":[{"name":"predAgent","position":{"x":1031.9511120028383,"y":843.4547531092195},"rotation":270,"scale":{"x":1,"y":1},"currentMotiv":"wander_predAgent"},{"name":"preyAgent","position":{"x":53.8065924308122,"y":60.80446756814986},"rotation":270,"scale":{"x":1,"y":1},"currentMotiv":"wander_preyAgent"}]},{"now":3867.6706,"entityStates":[{"name":"predAgent","position":{"x":1037.1469592828917,"y":851.9977176747637},"rotation":270,"scale":{"x":1,"y":1},"currentMotiv":"wander_predAgent"},{"name":"preyAgent","position":{"x":51.181147713044226,"y":72.21622945732435},"rotation":270,"scale":{"x":1,"y":1},"currentMotiv":"wander_preyAgent"}]},{"now":3901.0039,"entityStates":[{"name":"predAgent","position":{"x":1039.79074750035,"y":856.2412235543404},"rotation":270,"scale":{"x":1,"y":1},"currentMotiv":"wander_predAgent"},{"name":"preyAgent","position":{"x":49.96530879269871,"y":78.005756982749},"rotation":270,"scale":{"x":1,"y":1},"currentMotiv":"wander_preyAgent"}]},{"now":3934.3372,"entityStates":[{"name":"predAgent","position":{"x":1042.5098706657252,"y":860.435562391108},"rotation":270,"scale":{"x":1,"y":1},"currentMotiv":"wander_predAgent"},{"name":"preyAgent","position":{"x":48.80141241489794,"y":83.83169661608189},"rotation":270,"scale":{"x":1,"y":1},"currentMotiv":"wander_preyAgent"}]},{"now":3967.6707,"entityStates":[{"name":"predAgent","position":{"x":1044.7058173843302,"y":862.4280796998652},"rotation":270,"scale":{"x":1,"y":1},"currentMotiv":"wander_predAgent"},{"name":"preyAgent","position":{"x":47.70221191134737,"y":89.68795674908843},"rotation":270,"scale":{"x":1,"y":1},"currentMotiv":"wander_preyAgent"}]},{"now":4001.004,"entityStates":[{"name":"predAgent","position":{"x":1046.3757312649382,"y":865.0960052574192},"rotation":270,"scale":{"x":1,"y":1},"currentMotiv":"wander_predAgent"},{"name":"preyAgent","position":{"x":46.67078960403379,"y":95.5690021728522},"rotation":270,"scale":{"x":1,"y":1},"currentMotiv":"wander_preyAgent"}]},{"now":4034.3372999999997,"entityStates":[{"name":"predAgent","position":{"x":1048.5690167036857,"y":867.1390881747657},"rotation":270,"scale":{"x":1,"y":1},"currentMotiv":"wander_predAgent"},{"name":"preyAgent","position":{"x":45.692158581506376,"y":101.4679117800209},"rotation":270,"scale":{"x":1,"y":1},"currentMotiv":"wander_preyAgent"}]},{"now":4067.6708000000003,"entityStates":[{"name":"predAgent","position":{"x":1051.8248317596351,"y":868.6577480406667},"rotation":270,"scale":{"x":1,"y":1},"currentMotiv":"wander_predAgent"},{"name":"preyAgent","position":{"x":44.810107350935915,"y":107.3874322606792},"rotation":270,"scale":{"x":1,"y":1},"currentMotiv":"wander_preyAgent"}]},{"now":4101.0041,"entityStates":[{"name":"predAgent","position":{"x":1055.4883150371566,"y":869.0795572702909},"rotation":270,"scale":{"x":1,"y":1},"currentMotiv":"wander_predAgent"},{"name":"preyAgent","position":{"x":44.00653235755196,"y":113.32261393306428},"rotation":270,"scale":{"x":1,"y":1},"currentMotiv":"wander_preyAgent"}]},{"now":4134.337399999999,"entityStates":[{"name":"predAgent","position":{"x":1059.3074070119471,"y":868.1955857874846},"rotation":270,"scale":{"x":1,"y":1},"currentMotiv":"wander_predAgent"},{"name":"preyAgent","position":{"x":43.21168358032709,"y":119.2619169153803},"rotation":270,"scale":{"x":1,"y":1},"currentMotiv":"wander_preyAgent"}]},{"now":4167.6709,"entityStates":[{"name":"predAgent","position":{"x":1064.924522833717,"y":864.4208438163585},"rotation":270,"scale":{"x":1,"y":1},"currentMotiv":"wander_predAgent"},{"name":"preyAgent","position":{"x":41.60986342365736,"y":131.14385293326404},"rotation":270,"scale":{"x":1,"y":1},"currentMotiv":"wander_preyAgent"}]},{"now":4201.004199999999,"entityStates":[{"name":"predAgent","position":{"x":1066.8518645324743,"y":861.2623767798405},"rotation":270,"scale":{"x":1,"y":1},"currentMotiv":"wander_predAgent"},{"name":"preyAgent","position":{"x":40.8484821685247,"y":137.09191368619202},"rotation":270,"scale":{"x":1,"y":1},"currentMotiv":"wander_preyAgent"}]},{"now":4234.3375,"entityStates":[{"name":"predAgent","position":{"x":1067.630970913613,"y":857.2648954927316},"rotation":270,"scale":{"x":1,"y":1},"currentMotiv":"wander_predAgent"},{"name":"preyAgent","position":{"x":40.08433130368298,"y":143.04062302455583},"rotation":270,"scale":{"x":1,"y":1},"currentMotiv":"wander_preyAgent"}]},{"now":4267.671,"entityStates":[{"name":"predAgent","position":{"x":1067.2302617336165,"y":852.93292071821},"rotation":270,"scale":{"x":1,"y":1},"currentMotiv":"wander_predAgent"},{"name":"preyAgent","position":{"x":39.33455110121455,"y":148.9918408462376},"rotation":270,"scale":{"x":1,"y":1},"currentMotiv":"wander_preyAgent"}]},{"now":4301.0043,"entityStates":[{"name":"predAgent","position":{"x":1066.0296219695772,"y":848.5491195370556},"rotation":270,"scale":{"x":1,"y":1},"currentMotiv":"wander_predAgent"},{"name":"preyAgent","position":{"x":40.222141559243056,"y":152.8922750792271},"rotation":270,"scale":{"x":1,"y":1},"currentMotiv":"wander_preyAgent"}]},{"now":4334.3376,"entityStates":[{"name":"predAgent","position":{"x":1064.3123012060505,"y":844.1938487794571},"rotation":270,"scale":{"x":1,"y":1},"currentMotiv":"wander_predAgent"},{"name":"preyAgent","position":{"x":42.73100494710338,"y":156.50204946474},"rotation":270,"scale":{"x":1,"y":1},"currentMotiv":"wander_preyAgent"}]},{"now":4367.6711,"entityStates":[{"name":"predAgent","position":{"x":1062.2828686616106,"y":839.8692373212265},"rotation":270,"scale":{"x":1,"y":1},"currentMotiv":"wander_predAgent"},{"name":"preyAgent","position":{"x":46.902381216248436,"y":158.99801998473},"rotation":270,"scale":{"x":1,"y":1},"currentMotiv":"wander_preyAgent"}]},{"now":4401.0044,"entityStates":[{"name":"predAgent","position":{"x":1060.07937102155,"y":835.5555633321081},"rotation":270,"scale":{"x":1,"y":1},"currentMotiv":"wander_predAgent"},{"name":"preyAgent","position":{"x":52.08279078137096,"y":159.44191083541813},"rotation":270,"scale":{"x":1,"y":1},"currentMotiv":"wander_preyAgent"}]},{"now":4434.3377,"entityStates":[{"name":"predAgent","position":{"x":1057.7808021670023,"y":831.2387129609235},"rotation":270,"scale":{"x":1,"y":1},"currentMotiv":"wander_predAgent"},{"name":"preyAgent","position":{"x":57.27472952069047,"y":157.819339057863},"rotation":270,"scale":{"x":1,"y":1},"currentMotiv":"wander_preyAgent"}]},{"now":4467.6712,"entityStates":[{"name":"predAgent","position":{"x":1053.0724896469535,"y":822.5644558262009},"rotation":270,"scale":{"x":1,"y":1},"currentMotiv":"wander_predAgent"},{"name":"preyAgent","position":{"x":66.56186471339421,"y":151.37677132981943},"rotation":270,"scale":{"x":1,"y":1},"currentMotiv":"wander_preyAgent"}]},{"now":4501.0045,"entityStates":[{"name":"predAgent","position":{"x":1050.7333920901456,"y":818.1881689908745},"rotation":270,"scale":{"x":1,"y":1},"currentMotiv":"wander_predAgent"},{"name":"preyAgent","position":{"x":70.7276258834537,"y":147.33055555742615},"rotation":270,"scale":{"x":1,"y":1},"currentMotiv":"wander_preyAgent"}]},{"now":4534.3378,"entityStates":[{"name":"predAgent","position":{"x":1048.4204535879103,"y":813.7852550293202},"rotation":270,"scale":{"x":1,"y":1},"currentMotiv":"wander_predAgent"},{"name":"preyAgent","position":{"x":74.69684432308577,"y":143.0125433928009},"rotation":270,"scale":{"x":1,"y":1},"currentMotiv":"wander_preyAgent"}]},{"now":4567.6713,"entityStates":[{"name":"predAgent","position":{"x":1046.1309751270799,"y":809.3611520886686},"rotation":270,"scale":{"x":1,"y":1},"currentMotiv":"wander_predAgent"},{"name":"preyAgent","position":{"x":78.53701953116644,"y":138.52600524445123},"rotation":270,"scale":{"x":1,"y":1},"currentMotiv":"wander_preyAgent"}]},{"now":4601.0046,"entityStates":[{"name":"predAgent","position":{"x":1043.8834043171419,"y":804.9096094017139},"rotation":270,"scale":{"x":1,"y":1},"currentMotiv":"wander_predAgent"},{"name":"preyAgent","position":{"x":82.33539671361291,"y":133.96764579994434},"rotation":270,"scale":{"x":1,"y":1},"currentMotiv":"wander_preyAgent"}]},{"now":4634.3379,"entityStates":[{"name":"predAgent","position":{"x":1041.6744967114428,"y":800.4343846922701},"rotation":270,"scale":{"x":1,"y":1},"currentMotiv":"wander_predAgent"},{"name":"preyAgent","position":{"x":86.13177528438014,"y":129.38188051018986},"rotation":270,"scale":{"x":1,"y":1},"currentMotiv":"wander_preyAgent"}]},{"now":4667.671399999999,"entityStates":[{"name":"predAgent","position":{"x":1039.491750576127,"y":795.943236516857},"rotation":270,"scale":{"x":1,"y":1},"currentMotiv":"wander_predAgent"},{"name":"preyAgent","position":{"x":89.93106839293557,"y":124.78034843028688},"rotation":270,"scale":{"x":1,"y":1},"currentMotiv":"wander_preyAgent"}]},{"now":4701.0047,"entityStates":[{"name":"predAgent","position":{"x":1037.328735730979,"y":791.4403855844731},"rotation":270,"scale":{"x":1,"y":1},"currentMotiv":"wander_predAgent"},{"name":"preyAgent","position":{"x":93.70469309285798,"y":120.14540512189502},"rotation":270,"scale":{"x":1,"y":1},"currentMotiv":"wander_preyAgent"}]},{"now":4734.338,"entityStates":[{"name":"predAgent","position":{"x":1035.1755030768686,"y":786.9313298508542},"rotation":270,"scale":{"x":1,"y":1},"currentMotiv":"wander_predAgent"},{"name":"preyAgent","position":{"x":97.48520166931313,"y":115.5073067791387},"rotation":270,"scale":{"x":1,"y":1},"currentMotiv":"wander_preyAgent"}]},{"now":4767.6714999999995,"entityStates":[{"name":"predAgent","position":{"x":1030.8551324862674,"y":777.9170705093658},"rotation":270,"scale":{"x":1,"y":1},"currentMotiv":"wander_predAgent"},{"name":"preyAgent","position":{"x":105.1764018759623,"y":106.3231346798345},"rotation":270,"scale":{"x":1,"y":1},"currentMotiv":"wander_preyAgent"}]},{"now":4801.004800000001,"entityStates":[{"name":"predAgent","position":{"x":1028.6811385275887,"y":773.4156878297822},"rotation":270,"scale":{"x":1,"y":1},"currentMotiv":"wander_predAgent"},{"name":"preyAgent","position":{"x":109.10372446293525,"y":101.79521293847822},"rotation":270,"scale":{"x":1,"y":1},"currentMotiv":"wander_preyAgent"}]},{"now":4834.3381,"entityStates":[{"name":"predAgent","position":{"x":1026.511223160493,"y":768.9119842388044},"rotation":270,"scale":{"x":1,"y":1},"currentMotiv":"wander_predAgent"},{"name":"preyAgent","position":{"x":113.0930229081251,"y":97.31976228535757},"rotation":270,"scale":{"x":1,"y":1},"currentMotiv":"wander_preyAgent"}]},{"now":4867.671600000001,"entityStates":[{"name":"predAgent","position":{"x":1024.3297330245998,"y":764.4136651496058},"rotation":270,"scale":{"x":1,"y":1},"currentMotiv":"wander_predAgent"},{"name":"preyAgent","position":{"x":117.12289655254041,"y":92.87893136619667},"rotation":270,"scale":{"x":1,"y":1},"currentMotiv":"wander_preyAgent"}]},{"now":4901.0049,"entityStates":[{"name":"predAgent","position":{"x":1022.1426769830955,"y":759.9178424176704},"rotation":270,"scale":{"x":1,"y":1},"currentMotiv":"wander_predAgent"},{"name":"preyAgent","position":{"x":121.18596165244126,"y":88.46715444898894},"rotation":270,"scale":{"x":1,"y":1},"currentMotiv":"wander_preyAgent"}]},{"now":4934.3382,"entityStates":[{"name":"predAgent","position":{"x":1019.9361510747647,"y":755.4314778727988},"rotation":270,"scale":{"x":1,"y":1},"currentMotiv":"wander_predAgent"},{"name":"preyAgent","position":{"x":125.29287640233689,"y":84.0954937554978},"rotation":270,"scale":{"x":1,"y":1},"currentMotiv":"wander_preyAgent"}]},{"now":4967.671700000001,"entityStates":[{"name":"predAgent","position":{"x":1017.740374118748,"y":750.9398710996923},"rotation":270,"scale":{"x":1,"y":1},"currentMotiv":"wander_predAgent"},{"name":"preyAgent","position":{"x":129.46655876414138,"y":79.78760256179078},"rotation":270,"scale":{"x":1,"y":1},"currentMotiv":"wander_preyAgent"}]},{"now":5001.005,"entityStates":[{"name":"predAgent","position":{"x":1015.5665939293626,"y":746.4375173928971},"rotation":270,"scale":{"x":1,"y":1},"currentMotiv":"wander_predAgent"},{"name":"preyAgent","position":{"x":133.6940544599212,"y":75.53181634015341},"rotation":270,"scale":{"x":1,"y":1},"currentMotiv":"wander_preyAgent"}]},{"now":5034.3383,"entityStates":[{"name":"predAgent","position":{"x":1013.4267390631051,"y":741.9189549502382},"rotation":270,"scale":{"x":1,"y":1},"currentMotiv":"wander_predAgent"},{"name":"preyAgent","position":{"x":137.9293524771534,"y":71.28351595023814},"rotation":270,"scale":{"x":1,"y":1},"currentMotiv":"wander_preyAgent"}]},{"now":5067.6718,"entityStates":[{"name":"predAgent","position":{"x":1009.1678528410101,"y":732.8717369186262},"rotation":270,"scale":{"x":1,"y":1},"currentMotiv":"wander_predAgent"},{"name":"preyAgent","position":{"x":146.4124054580163,"y":62.79802282277754},"rotation":270,"scale":{"x":1,"y":1},"currentMotiv":"wander_preyAgent"}]},{"now":5101.0051,"entityStates":[{"name":"predAgent","position":{"x":1007.0488778307557,"y":728.3431393954863},"rotation":270,"scale":{"x":1,"y":1},"currentMotiv":"wander_predAgent"},{"name":"preyAgent","position":{"x":150.67278189967655,"y":58.574018383280645},"rotation":270,"scale":{"x":1,"y":1},"currentMotiv":"wander_preyAgent"}]},{"now":5134.3384,"entityStates":[{"name":"predAgent","position":{"x":1004.9313309523044,"y":723.8138230738991},"rotation":270,"scale":{"x":1,"y":1},"currentMotiv":"wander_predAgent"},{"name":"preyAgent","position":{"x":154.96476206553575,"y":54.3820922036431},"rotation":270,"scale":{"x":1,"y":1},"currentMotiv":"wander_preyAgent"}]},{"now":5167.6719,"entityStates":[{"name":"predAgent","position":{"x":1002.8296725550999,"y":719.2771372545309},"rotation":270,"scale":{"x":1,"y":1},"currentMotiv":"wander_predAgent"},{"name":"preyAgent","position":{"x":159.26951308390693,"y":50.20306357490684},"rotation":270,"scale":{"x":1,"y":1},"currentMotiv":"wander_preyAgent"}]},{"now":5201.0052,"entityStates":[{"name":"predAgent","position":{"x":1000.7515399364113,"y":714.7296349639084},"rotation":270,"scale":{"x":1,"y":1},"currentMotiv":"wander_predAgent"},{"name":"preyAgent","position":{"x":163.5492503050479,"y":45.99882075667482},"rotation":270,"scale":{"x":1,"y":1},"currentMotiv":"wander_preyAgent"}]},{"now":5234.3385,"entityStates":[{"name":"predAgent","position":{"x":998.6961150615846,"y":710.171793436274},"rotation":270,"scale":{"x":1,"y":1},"currentMotiv":"wander_predAgent"},{"name":"preyAgent","position":{"x":167.80977657525608,"y":41.774830372554725},"rotation":270,"scale":{"x":1,"y":1},"currentMotiv":"wander_preyAgent"}]},{"now":5267.6720000000005,"entityStates":[{"name":"predAgent","position":{"x":996.675762285226,"y":705.5983880856835},"rotation":270,"scale":{"x":1,"y":1},"currentMotiv":"wander_predAgent"},{"name":"preyAgent","position":{"x":172.0531096183361,"y":37.533379209669874},"rotation":270,"scale":{"x":1,"y":1},"currentMotiv":"wander_preyAgent"}]},{"now":5301.0053,"entityStates":[{"name":"predAgent","position":{"x":994.6773356810116,"y":701.0152895301902},"rotation":270,"scale":{"x":1,"y":1},"currentMotiv":"wander_predAgent"},{"name":"preyAgent","position":{"x":176.85770119865654,"y":35.03947882129812},"rotation":270,"scale":{"x":1,"y":1},"currentMotiv":"wander_preyAgent"}]},{"now":5334.3386,"entityStates":[{"name":"predAgent","position":{"x":992.6642648855648,"y":696.438781121894},"rotation":270,"scale":{"x":1,"y":1},"currentMotiv":"wander_predAgent"},{"name":"preyAgent","position":{"x":180.56304161208033,"y":34.47311612511217},"rotation":270,"scale":{"x":1,"y":1},"currentMotiv":"wander_preyAgent"}]},{"now":5367.6721,"entityStates":[{"name":"predAgent","position":{"x":988.5851658009896,"y":687.3090354141726},"rotation":270,"scale":{"x":1,"y":1},"currentMotiv":"wander_predAgent"},{"name":"preyAgent","position":{"x":187.9847899373897,"y":37.43469583875143},"rotation":270,"scale":{"x":1,"y":1},"currentMotiv":"wander_preyAgent"}]},{"now":5401.0054,"entityStates":[{"name":"predAgent","position":{"x":986.5184038390769,"y":682.7563512329635},"rotation":270,"scale":{"x":1,"y":1},"currentMotiv":"wander_predAgent"},{"name":"preyAgent","position":{"x":190.94210010724498,"y":40.43658016868655},"rotation":270,"scale":{"x":1,"y":1},"currentMotiv":"wander_preyAgent"}]},{"now":5434.338699999999,"entityStates":[{"name":"predAgent","position":{"x":984.4199934355969,"y":678.2182320114692},"rotation":270,"scale":{"x":1,"y":1},"currentMotiv":"wander_predAgent"},{"name":"preyAgent","position":{"x":194.19800449863087,"y":43.794407189701445},"rotation":270,"scale":{"x":1,"y":1},"currentMotiv":"wander_preyAgent"}]},{"now":5467.6722,"entityStates":[{"name":"predAgent","position":{"x":982.2939809369028,"y":673.6929292760967},"rotation":270,"scale":{"x":1,"y":1},"currentMotiv":"wander_predAgent"},{"name":"preyAgent","position":{"x":197.87317060201173,"y":47.277639975989075},"rotation":270,"scale":{"x":1,"y":1},"currentMotiv":"wander_preyAgent"}]},{"now":5501.0055,"entityStates":[{"name":"predAgent","position":{"x":980.1338710142401,"y":669.1838403674614},"rotation":270,"scale":{"x":1,"y":1},"currentMotiv":"wander_predAgent"},{"name":"preyAgent","position":{"x":201.88148146426278,"y":50.81186300007629},"rotation":270,"scale":{"x":1,"y":1},"currentMotiv":"wander_preyAgent"}]},{"now":5534.3387999999995,"entityStates":[{"name":"predAgent","position":{"x":977.9352146282617,"y":664.6934538716993},"rotation":270,"scale":{"x":1,"y":1},"currentMotiv":"wander_predAgent"},{"name":"preyAgent","position":{"x":206.1449013437699,"y":54.35002110540124},"rotation":270,"scale":{"x":1,"y":1},"currentMotiv":"wander_preyAgent"}]},{"now":5567.6723,"entityStates":[{"name":"predAgent","position":{"x":975.6977681562225,"y":660.2222676082398},"rotation":270,"scale":{"x":1,"y":1},"currentMotiv":"wander_predAgent"},{"name":"preyAgent","position":{"x":210.60774269806507,"y":57.860110989657},"rotation":270,"scale":{"x":1,"y":1},"currentMotiv":"wander_preyAgent"}]},{"now":5601.0055999999995,"entityStates":[{"name":"predAgent","position":{"x":973.4066973063955,"y":655.7785366929852},"rotation":270,"scale":{"x":1,"y":1},"currentMotiv":"wander_predAgent"},{"name":"preyAgent","position":{"x":215.19136547077326,"y":61.37213426211501},"rotation":270,"scale":{"x":1,"y":1},"currentMotiv":"wander_preyAgent"}]},{"now":5634.338900000001,"entityStates":[{"name":"predAgent","position":{"x":971.0822160531098,"y":651.3520474259171},"rotation":270,"scale":{"x":1,"y":1},"currentMotiv":"wander_predAgent"},{"name":"preyAgent","position":{"x":219.85746188700327,"y":64.88746786019917},"rotation":270,"scale":{"x":1,"y":1},"currentMotiv":"wander_preyAgent"}]},{"now":5667.6723999999995,"entityStates":[{"name":"predAgent","position":{"x":966.3895639690617,"y":642.5221554729882},"rotation":270,"scale":{"x":1,"y":1},"currentMotiv":"wander_predAgent"},{"name":"preyAgent","position":{"x":229.21601804128247,"y":72.09197722132008},"rotation":270,"scale":{"x":1,"y":1},"currentMotiv":"wander_preyAgent"}]},{"now":5701.0057,"entityStates":[{"name":"predAgent","position":{"x":963.9974759298794,"y":638.1318264732473},"rotation":270,"scale":{"x":1,"y":1},"currentMotiv":"wander_predAgent"},{"name":"preyAgent","position":{"x":233.88295267366576,"y":75.7752035365524},"rotation":270,"scale":{"x":1,"y":1},"currentMotiv":"wander_preyAgent"}]},{"now":5734.339,"entityStates":[{"name":"predAgent","position":{"x":961.5890318204187,"y":633.7503516144598},"rotation":270,"scale":{"x":1,"y":1},"currentMotiv":"wander_predAgent"},{"name":"preyAgent","position":{"x":238.53155703744594,"y":79.5076291501307},"rotation":270,"scale":{"x":1,"y":1},"currentMotiv":"wander_preyAgent"}]},{"now":5767.6725,"entityStates":[{"name":"predAgent","position":{"x":959.1493321436211,"y":629.3862869124556},"rotation":270,"scale":{"x":1,"y":1},"currentMotiv":"wander_predAgent"},{"name":"preyAgent","position":{"x":243.139262368187,"y":83.30787830351746},"rotation":270,"scale":{"x":1,"y":1},"currentMotiv":"wander_preyAgent"}]},{"now":5801.005800000001,"entityStates":[{"name":"predAgent","position":{"x":956.6705756956561,"y":625.0443311394995},"rotation":270,"scale":{"x":1,"y":1},"currentMotiv":"wander_predAgent"},{"name":"preyAgent","position":{"x":247.6926748405366,"y":87.18504362102861},"rotation":270,"scale":{"x":1,"y":1},"currentMotiv":"wander_preyAgent"}]},{"now":5834.3391,"entityStates":[{"name":"predAgent","position":{"x":954.171152800867,"y":620.7141310954861},"rotation":270,"scale":{"x":1,"y":1},"currentMotiv":"wander_predAgent"},{"name":"preyAgent","position":{"x":252.15791898924343,"y":91.17030679927157},"rotation":270,"scale":{"x":1,"y":1},"currentMotiv":"wander_preyAgent"}]},{"now":5867.6726,"entityStates":[{"name":"predAgent","position":{"x":951.6694788770707,"y":616.3851882865234},"rotation":270,"scale":{"x":1,"y":1},"currentMotiv":"wander_predAgent"},{"name":"preyAgent","position":{"x":256.537913992701,"y":95.25505074206315},"rotation":270,"scale":{"x":1,"y":1},"currentMotiv":"wander_preyAgent"}]},{"now":5901.0059,"entityStates":[{"name":"predAgent","position":{"x":949.179699228338,"y":612.0493885439475},"rotation":270,"scale":{"x":1,"y":1},"currentMotiv":"wander_predAgent"},{"name":"preyAgent","position":{"x":260.85056427036363,"y":99.41540263826695},"rotation":270,"scale":{"x":1,"y":1},"currentMotiv":"wander_preyAgent"}]},{"now":5934.3392,"entityStates":[{"name":"predAgent","position":{"x":946.7088810869777,"y":607.7027394917238},"rotation":270,"scale":{"x":1,"y":1},"currentMotiv":"wander_predAgent"},{"name":"preyAgent","position":{"x":265.1009893536713,"y":103.64234644281156},"rotation":270,"scale":{"x":1,"y":1},"currentMotiv":"wander_preyAgent"}]},{"now":5967.672699999999,"entityStates":[{"name":"predAgent","position":{"x":941.8284702066444,"y":598.9749352558505},"rotation":270,"scale":{"x":1,"y":1},"currentMotiv":"wander_predAgent"},{"name":"preyAgent","position":{"x":273.4177990920288,"y":112.28253627647031},"rotation":270,"scale":{"x":1,"y":1},"currentMotiv":"wander_preyAgent"}]},{"now":6001.006,"entityStates":[{"name":"predAgent","position":{"x":939.4291964135114,"y":594.5883741870832},"rotation":270,"scale":{"x":1,"y":1},"currentMotiv":"wander_predAgent"},{"name":"preyAgent","position":{"x":277.48487802721024,"y":116.69043582398446},"rotation":270,"scale":{"x":1,"y":1},"currentMotiv":"wander_preyAgent"}]},{"now":6002,"entityStates":[{"name":"predAgent","position":{"x":939.4291964135114,"y":594.5883741870832},"rotation":270,"scale":{"x":1,"y":1},"currentMotiv":null},{"name":"preyAgent","position":{"x":277.48487802721024,"y":116.69043582398446},"rotation":270,"scale":{"x":1,"y":1},"currentMotiv":null}]}]}